README.md
setup.cfg
setup.py
muda/__init__.py
muda/base.py
muda/core.py
muda/version.py
muda.egg-info/PKG-INFO
muda.egg-info/SOURCES.txt
muda.egg-info/dependency_links.txt
muda.egg-info/requires.txt
muda.egg-info/top_level.txt
muda/deformers/__init__.py
muda/deformers/background.py
muda/deformers/colorednoise.py
muda/deformers/ir.py
muda/deformers/pitch.py
muda/deformers/sox.py
muda/deformers/time.py
muda/deformers/util.py
muda/deformers/data/drc_presets.json