Metadata-Version: 2.1
Name: muda
Version: 0.4.0
Summary: Musical data augmentation
Home-page: http://github.com/bmcfee/muda
Author: Brian McFee
Author-email: brian.mcfee@nyu.edu
License: ISC
Download-URL: http://github.com/bmcfee/muda/releases
Keywords: audio music sound
Platform: UNKNOWN
Classifier: License :: OSI Approved :: ISC License (ISCL)
Classifier: Programming Language :: Python
Classifier: Development Status :: 3 - Alpha
Classifier: Intended Audience :: Developers
Classifier: Topic :: Multimedia :: Sound/Audio :: Analysis
Classifier: Programming Language :: Python :: 2
Classifier: Programming Language :: Python :: 2.7
Classifier: Programming Language :: Python :: 3
Classifier: Programming Language :: Python :: 3.4
Classifier: Programming Language :: Python :: 3.5
Classifier: Programming Language :: Python :: 3.6
Classifier: Programming Language :: Python :: 3.7
Provides-Extra: docs
Provides-Extra: tests
